MANIFEST.in
README.md
setup.py
bin/mirror-call
bin/mirror-seq
bin/mirror-trim
mirror_seq/__init__.py
mirror_seq/hmc_calling.py
mirror_seq/trimming.py
mirror_seq/version.py
mirror_seq.egg-info/PKG-INFO
mirror_seq.egg-info/SOURCES.txt
mirror_seq.egg-info/dependency_links.txt
mirror_seq.egg-info/requires.txt
mirror_seq.egg-info/top_level.txt