Metadata-Version: 1.1
Name: mirror-seq
Version: 0.2.6
Summary: The bioinformatics tool for Mirror-seq.
Home-page: https://github.com/Zymo-Research/mirror-seq
Author: Hunter Chung
Author-email: b89603112@gmail.com
License: Apache License 2.0
Keywords: mirror sequencing next-gen hydroxymethylation bisulfite bioinformatics
Platform: UNKNOWN
Classifier: Programming Language :: Python :: 2.7
